math_quiz/__init__.py
math_quiz/math_quiz.py
math_quiz/tests_math_quiz.py
math_quiz_Eid-1.0.dist-info/LICENSE
math_quiz_Eid-1.0.dist-info/METADATA
math_quiz_Eid-1.0.dist-info/WHEEL
math_quiz_Eid-1.0.dist-info/top_level.txt
math_quiz_Eid-1.0.dist-info/RECORD
